{
  "schemaVersion": 1,
  "generatedAtUtc": "2026-06-24T16:37:15Z",
  "latestLessonDate": "2026-06-25",
  "days": [
    {
      "lessonDate": "2026-06-25",
      "manifestUrl": "https://shoya9696.github.io/daily-shadowing-content/lessons/2026-06-25.json",
      "isLatest": true,
      "lessons": [
        {
          "level": "beginner",
          "title": "The Benefits of Walking at Work",
          "durationSeconds": 39
        },
        {
          "level": "intermediate",
          "title": "Boosting Energy Through Short Walks",
          "durationSeconds": 51
        },
        {
          "level": "advanced",
          "title": "Optimizing Office Wellness Through Movement",
          "durationSeconds": 74
        }
      ]
    },
    {
      "lessonDate": "2026-06-24",
      "manifestUrl": "https://shoya9696.github.io/daily-shadowing-content/lessons/2026-06-24.json",
      "isLatest": false,
      "lessons": [
        {
          "level": "beginner",
          "title": "The Benefits of Walking at Work",
          "durationSeconds": 35
        },
        {
          "level": "intermediate",
          "title": "Improving Workplace Wellness Through Movement",
          "durationSeconds": 54
        },
        {
          "level": "advanced",
          "title": "The Science of Movement for Mental and Physical Well-being",
          "durationSeconds": 77
        }
      ]
    },
    {
      "lessonDate": "2026-06-23",
      "manifestUrl": "https://shoya9696.github.io/daily-shadowing-content/lessons/2026-06-23.json",
      "isLatest": false,
      "lessons": [
        {
          "level": "beginner",
          "title": "Short Breaks at Work",
          "durationSeconds": 10
        },
        {
          "level": "intermediate",
          "title": "Resetting Focus During the Day",
          "durationSeconds": 14
        },
        {
          "level": "advanced",
          "title": "Micro-breaks and Sustainable Focus",
          "durationSeconds": 21
        }
      ]
    }
  ]
}
